kilroy_module_py_shared/__init__.py
kilroy_module_py_shared/errors.py
kilroy_module_py_shared/messages.py
kilroy_module_py_shared/metadata.py
kilroy_module_py_shared/models.py
kilroy_module_py_shared/posts.py
kilroy_module_py_shared/resources/__init__.py
kilroy_module_py_shared-0.7.0.dist-info/LICENSE
kilroy_module_py_shared-0.7.0.dist-info/WHEEL
kilroy_module_py_shared-0.7.0.dist-info/METADATA
kilroy_module_py_shared-0.7.0.dist-info/RECORD
