Metadata-Version: 2.1
Name: kilroy-module-py-shared
Version: 0.7.0
Summary: shared code for kilroy module SDKs in Python 🤝
Home-page: https://github.com/kilroybot/kilroy-module-py-shared
Author: kilroy
Author-email: kilroymail@pm.me
Requires-Python: >=3.10,<4.0
Classifier: License :: OSI Approved :: MIT License
Classifier: Operating System :: OS Independent
Classifier: Programming Language :: Python :: 3
Classifier: Programming Language :: Python :: 3.10
Requires-Dist: betterproto (>=2.0.0b5,<3.0.0)
Requires-Dist: jsonschema (>=4.7,<5.0)
Requires-Dist: pydantic (>=1.9,<2.0)
Requires-Dist: pyhumps (>=3.7,<4.0)
Project-URL: Documentation, https://kilroybot.github.io/kilroy-module-py-shared
Project-URL: Repository, https://github.com/kilroybot/kilroy-module-py-shared
